dndchar/__init__.py
dndchar/backgrounds.py
dndchar/classes.py
dndchar/command_line.py
dndchar/data.py
dndchar/player.py
dndchar/races.py
dndchar/scores.py
dndchar/util.py
dndchar-1.1.1.dist-info/METADATA
dndchar-1.1.1.dist-info/WHEEL
dndchar-1.1.1.dist-info/entry_points.txt
dndchar-1.1.1.dist-info/top_level.txt
dndchar-1.1.1.dist-info/RECORD
